concrete_datastore/__init__.py
concrete_datastore/admin/__init__.py
concrete_datastore/admin/admin.py
concrete_datastore/admin/admin_form.py
concrete_datastore/admin/admin_models.py
concrete_datastore/admin/admin_site.py
concrete_datastore/api/__init__.py
concrete_datastore/api/v1/__init__.py
concrete_datastore/api/v1/authentication.py
concrete_datastore/api/v1/datetime.py
concrete_datastore/api/v1/exceptions.py
concrete_datastore/api/v1/filters.py
concrete_datastore/api/v1/pagination.py
concrete_datastore/api/v1/permissions.py
concrete_datastore/api/v1/serializers.py
concrete_datastore/api/v1/signals.py
concrete_datastore/api/v1/urls.py
concrete_datastore/api/v1/validators.py
concrete_datastore/api/v1/views.py
concrete_datastore/api/v1_1/__init__.py
concrete_datastore/api/v1_1/permissions.py
concrete_datastore/api/v1_1/serializers.py
concrete_datastore/api/v1_1/urls.py
concrete_datastore/api/v1_1/views.py
concrete_datastore/authentication/__init__.py
concrete_datastore/authentication/auth.py
concrete_datastore/authentication/oauth2_utils.py
concrete_datastore/concrete/__init__.py
concrete_datastore/concrete/apps.py
concrete_datastore/concrete/constants.py
concrete_datastore/concrete/meta.py
concrete_datastore/concrete/middleware.py
concrete_datastore/concrete/models.py
concrete_datastore/concrete/password.py
concrete_datastore/concrete/urls.py
concrete_datastore/concrete/views.py
concrete_datastore/concrete/automation/__init__.py
concrete_datastore/concrete/automation/signal_processor.py
concrete_datastore/concrete/automation/signals.py
concrete_datastore/concrete/automation/tasks.py
concrete_datastore/concrete/locale/.gitignore
concrete_datastore/concrete/management/__init__.py
concrete_datastore/concrete/management/commands/__init__.py
concrete_datastore/concrete/management/commands/create_superuser.py
concrete_datastore/concrete/management/commands/create_superuser_with_email.py
concrete_datastore/concrete/management/commands/init_app.py
concrete_datastore-1.28.0.dist-info/LICENSE
concrete_datastore-1.28.0.dist-info/METADATA
concrete_datastore-1.28.0.dist-info/WHEEL
concrete_datastore-1.28.0.dist-info/entry_points.txt
concrete_datastore-1.28.0.dist-info/top_level.txt
concrete_datastore-1.28.0.dist-info/RECORD
