Metadata-Version: 2.1
Name: concrete-datastore
Version: 1.28.0
Summary: A highly versatile REST Datastore
Home-page: https://customer.caas.microservices.rest/
Author: Netsach
Author-email: contact@netsach.org
License: GNU GENERAL PUBLIC LICENSE Version 3
Project-URL: Bug Tracker, https://github.com/Netsach/concrete-datastore/issues
Project-URL: Documentation, https://concrete-datastore.netsach.org/en/latest/
Project-URL: Source Code, https://github.com/Netsach/concrete-datastore/
Project-URL: Tests Coverage, https://codecov.io/gh/Netsach/concrete-datastore
Platform: UNKNOWN
Classifier: Programming Language :: Python :: 3.6
Classifier: Programming Language :: Python :: 3.7
Classifier: Programming Language :: Python :: 3.8
Requires-Dist: Django (<2.3,>=2.2)
Requires-Dist: django-cors-headers (<2,>=1.3.1)
Requires-Dist: django-extensions (<2,>=1.7)
Requires-Dist: django-filter (<3,>=2.1.0)
Requires-Dist: django-otp (<1,>=0.7.0)
Requires-Dist: djangorestframework (==3.10.2)
Requires-Dist: djangorestframework-gis (<0.18.0,>=0.17.0)
Requires-Dist: drf-extra-fields (<4,>=3.0.4)
Requires-Dist: social-auth-app-django (<3.2,>=3.1.0)
Requires-Dist: social-auth-core (<3.3,>=3.2.0)
Requires-Dist: psycopg2-binary (<3,>=2.8.1)
Requires-Dist: concrete-mailer (<3,>=2.13.0)
Requires-Dist: pendulum (<3,>=2.0)
Requires-Dist: Pillow (<9,>=8)
Requires-Dist: pytz (>=2018.5)
Requires-Dist: requests (<3,>=2.13.0)
Requires-Dist: pyyaml (<6,>=5.1.2)
Requires-Dist: uritemplate (<4,>=3.0.0)
Requires-Dist: six (<2,>=1.12)
Requires-Dist: python-slugify (<4,>=3.0.3)
Requires-Dist: celery (<5,>=4.3)
Requires-Dist: redis (<4,>=3.2)
Provides-Extra: dev
Requires-Dist: ipython ; extra == 'dev'
Requires-Dist: django-debug-toolbar ; extra == 'dev'
Provides-Extra: docs
Requires-Dist: mkdocs (<2,>=1.0.4) ; extra == 'docs'
Requires-Dist: mkdocs-material (<4.5,>=4.4.3) ; extra == 'docs'
Provides-Extra: full
Requires-Dist: ipython ; extra == 'full'
Requires-Dist: django-debug-toolbar ; extra == 'full'
Requires-Dist: mock ; extra == 'full'
Requires-Dist: pytest-django ; extra == 'full'
Requires-Dist: pytest-cov ; extra == 'full'
Requires-Dist: pytest ; extra == 'full'
Requires-Dist: codecov ; extra == 'full'
Requires-Dist: bandit ; extra == 'full'
Requires-Dist: pylint ; extra == 'full'
Requires-Dist: black ; extra == 'full'
Provides-Extra: quality
Requires-Dist: pylint ; extra == 'quality'
Requires-Dist: black ; extra == 'quality'
Provides-Extra: security
Requires-Dist: bandit ; extra == 'security'
Provides-Extra: tests
Requires-Dist: mock ; extra == 'tests'
Requires-Dist: pytest-django ; extra == 'tests'
Requires-Dist: pytest-cov ; extra == 'tests'
Requires-Dist: pytest ; extra == 'tests'
Requires-Dist: codecov ; extra == 'tests'
